tardis_dev/__init__.py
tardis_dev/datasets/__init__.py
tardis_dev/datasets/download.py
tardis_dev/get_exchange_details.py
tardis_dev-2.1.2.dist-info/LICENSE
tardis_dev-2.1.2.dist-info/WHEEL
tardis_dev-2.1.2.dist-info/METADATA
tardis_dev-2.1.2.dist-info/RECORD
